caper/__init__.py
caper/__main__.py
caper/arg_tool.py
caper/backward_compatibility.py
caper/caper_args.py
caper/caper_backend_conf.py
caper/caper_base.py
caper/caper_client.py
caper/caper_init.py
caper/caper_labels.py
caper/caper_runner.py
caper/caper_wdl_parser.py
caper/caper_workflow_opts.py
caper/cli.py
caper/cli_hpc.py
caper/cromwell.py
caper/cromwell_backend.py
caper/cromwell_metadata.py
caper/cromwell_rest_api.py
caper/cromwell_workflow_monitor.py
caper/dict_tool.py
caper/hocon_string.py
caper/hpc.py
caper/nb_subproc_thread.py
caper/resource_analysis.py
caper/server_heartbeat.py
caper/singularity.py
caper/wdl_parser.py
caper-2.3.2.data/scripts/caper
caper-2.3.2.data/scripts/create_instance.sh
caper-2.3.2.data/scripts/run_mysql_server_docker.sh
caper-2.3.2.data/scripts/run_mysql_server_singularity.sh
tests/__init__.py
tests/conftest.py
tests/example_wdl.py
tests/test_arg_tool.py
tests/test_caper_labels.py
tests/test_caper_wdl_parser.py
tests/test_caper_workflow_opts.py
tests/test_cli_run.py
tests/test_cli_server_client_gcp.py
tests/test_cromwell.py
tests/test_cromwell_backend.py
tests/test_cromwell_metadata.py
tests/test_cromwell_rest_api.py
tests/test_dict_tool.py
tests/test_hocon_string.py
tests/test_nb_subproc_thread.py
tests/test_resource_analysis.py
tests/test_server_heartbeat.py
tests/test_singularity.py
tests/test_wdl_parser.py
caper-2.3.2.dist-info/LICENSE
caper-2.3.2.dist-info/METADATA
caper-2.3.2.dist-info/WHEEL
caper-2.3.2.dist-info/top_level.txt
caper-2.3.2.dist-info/RECORD
