Metadata-Version: 2.1
Name: caper
Version: 2.3.2
Summary: Cromwell Assisted Pipeline ExecutoR
Home-page: https://github.com/ENCODE-DCC/caper
Author: Jin Lee
Author-email: leepc12@gmail.com
Classifier: Programming Language :: Python :: 3
Classifier: License :: OSI Approved :: MIT License
Classifier: Operating System :: POSIX :: Linux
Requires-Python: >=3.6
License-File: LICENSE
Requires-Dist: pyhocon (>=0.3.53)
Requires-Dist: requests (>=2.20)
Requires-Dist: pyopenssl
Requires-Dist: autouri (>=0.4.4)
Requires-Dist: miniwdl (>=0.7.0)
Requires-Dist: humanfriendly
Requires-Dist: numpy (>=1.8.2)
Requires-Dist: pandas (>=1.0)
Requires-Dist: scikit-learn (>=0.19.2)
Requires-Dist: matplotlib (>=1.5)
Requires-Dist: six (>=1.13.0)
